nothion/__init__.py
nothion/_config.py
nothion/_notion_api.py
nothion/_notion_parsers.py
nothion/_notion_payloads.py
nothion/_notion_table_headers.py
nothion/notion_client.py
nothion/py.typed
nothion/data_models/expense_log.py
nothion/data_models/personal_stats.py
nothion-0.4.9.dist-info/licenses/LICENSE
nothion-0.4.9.dist-info/METADATA
nothion-0.4.9.dist-info/WHEEL
nothion-0.4.9.dist-info/top_level.txt
nothion-0.4.9.dist-info/RECORD
