Metadata-Version: 2.4
Name: nothion
Version: 0.4.9
Summary: Yet another unofficial Notion API client.
Author-email: anggelomos <anggelomos@outlook.com>
Project-URL: repository, https://github.com/anggelomos/nothion
Classifier: Programming Language :: Python :: 3.10
Requires-Python: >=3.10
License-File: LICENSE
Requires-Dist: tickthon
Requires-Dist: requests
Requires-Dist: attrs
Dynamic: license-file
